dora_explorer/__init__.py
dora_explorer/distance_locator.py
dora_explorer/find_path.py
dora_explorer/tiny_explore.py
dora_explorer/travel_places.py
dora_explorer/useful_plots.py
dora_explorer-0.2.2.dist-info/LICENSE.txt
dora_explorer-0.2.2.dist-info/METADATA
dora_explorer-0.2.2.dist-info/WHEEL
dora_explorer-0.2.2.dist-info/top_level.txt
dora_explorer-0.2.2.dist-info/RECORD
