Metadata-Version: 2.1
Name: dora-explorer
Version: 0.2.2
Summary: Python project to get insights and distances to explore the places of the Earth
Home-page: https://github.com/msameeruddin/dora_explorer
Author: Mohammed Sameeruddin
Author-email: msameeruddin1998@gmail.com
License: MIT
Keywords: Geo-Explorer,Python Explorer,Geo-Traveller,Python 3
Platform: UNKNOWN
Classifier: License :: OSI Approved :: MIT License
Classifier: Programming Language :: Python :: 3
Classifier: Programming Language :: Python :: 3.7
Requires-Dist: plotly
Requires-Dist: mpu
Requires-Dist: unidecode
Requires-Dist: geonamescache
Requires-Dist: requests
